{
  "_class": "shapeGroup",
  "clippingMaskMode": 0,
  "do_objectID": "6C14AC3D-FB8B-4698-B27D-9161236875FB",
  "exportOptions": {
    "_class": "exportOptions",
    "exportFormats": [
    ],
    "includedLayerIds": [
    ],
    "layerOptions": 0,
    "shouldTrim": false
  },
  "frame": {
    "_class": "rect",
    "constrainProportions": true,
    "height": 33,
    "width": 33,
    "x": 27.5,
    "y": 27.5
  },
  "hasClickThrough": false,
  "hasClippingMask": false,
  "isFlippedHorizontal": false,
  "isFlippedVertical": false,
  "isLocked": false,
  "isVisible": true,
  "layerListExpandedType": 0,
  "layers": [
    {
      "class": "shapePath",
      "id": "49099441-D2A2-4375-ADAA-18DAA7088B16"
    },
    {
      "class": "shapePath",
      "id": "678C891D-C3F5-4839-BCF7-4E0606AB379C"
    }
  ],
  "name": "Book",
  "nameIsFixed": true,
  "resizingConstraint": 63,
  "resizingType": 0,
  "rotation": 0,
  "shouldBreakMaskChain": false,
  "style": {
    "_class": "style",
    "endDecorationType": 0,
    "fills": [
      {
        "_class": "fill",
        "color": {
          "_class": "color",
          "alpha": 1,
          "blue": 0.4,
          "green": 0.4,
          "red": 0.4
        },
        "fillType": 0,
        "isEnabled": true,
        "noiseIndex": 0,
        "noiseIntensity": 0,
        "patternFillType": 1,
        "patternTileScale": 1
      }
    ],
    "miterLimit": 10,
    "startDecorationType": 0
  },
  "userInfo": {
    "com.sketchplugins.wechat.selectionDom1": {
      "selection1": "C9F6C2A9-0888-4AA3-B30E-F31525CC0CFF"
    }
  },
  "windingRule": 1
}