{
  "_class": "group",
  "do_objectID": "C8DFEC08-0128-450F-A554-70A60C378436",
  "exportOptions": {
    "_class": "exportOptions",
    "exportFormats": [
    ],
    "includedLayerIds": [
    ],
    "layerOptions": 0,
    "shouldTrim": false
  },
  "frame": {
    "_class": "rect",
    "constrainProportions": false,
    "height": 400,
    "width": 663,
    "x": 69,
    "y": 80
  },
  "hasClickThrough": false,
  "isFlippedHorizontal": false,
  "isFlippedVertical": false,
  "isLocked": false,
  "isVisible": true,
  "layerListExpandedType": 0,
  "layers": [
    {
      "class": "shapeGroup",
      "id": "F1841511-269A-4984-9A71-BFB9CA0D38EB"
    },
    {
      "class": "shapeGroup",
      "id": "5AF19EC7-D79C-4A4E-BDDB-F99F89E178DA"
    },
    {
      "class": "shapeGroup",
      "id": "F9C975F7-51BE-4407-A5E2-1EFB0E9D72A8"
    },
    {
      "class": "group",
      "id": "07AEB1FD-C506-4411-93AE-10D76ADDFAED"
    }
  ],
  "name": "Power",
  "nameIsFixed": true,
  "resizingConstraint": 13,
  "resizingType": 0,
  "rotation": 0,
  "shouldBreakMaskChain": false,
  "style": {
    "_class": "style",
    "endDecorationType": 0,
    "miterLimit": 10,
    "startDecorationType": 0
  },
  "userInfo": {
    "com.sketchplugins.wechat.selectionDom1": {
      "selection1": "C8DFEC08-0128-450F-A554-70A60C378436"
    }
  }
}